UcbData8JisuanYuTuiduanSiweiZhongwenban/README.md
UcbData8JisuanYuTuiduanSiweiZhongwenban/__init__.py
UcbData8JisuanYuTuiduanSiweiZhongwenban/__main__.py
UcbData8JisuanYuTuiduanSiweiZhongwenban/file.epub
UcbData8JisuanYuTuiduanSiweiZhongwenban/index.html
UcbData8JisuanYuTuiduanSiweiZhongwenban/css/__init__.py
UcbData8JisuanYuTuiduanSiweiZhongwenban/css/annotations.css
UcbData8JisuanYuTuiduanSiweiZhongwenban/css/main.css
UcbData8JisuanYuTuiduanSiweiZhongwenban/css/normalize.css
UcbData8JisuanYuTuiduanSiweiZhongwenban/css/popup.css
UcbData8JisuanYuTuiduanSiweiZhongwenban/font/__init__.py
UcbData8JisuanYuTuiduanSiweiZhongwenban/font/fontello.eot
UcbData8JisuanYuTuiduanSiweiZhongwenban/font/fontello.svg
UcbData8JisuanYuTuiduanSiweiZhongwenban/font/fontello.ttf
UcbData8JisuanYuTuiduanSiweiZhongwenban/font/fontello.woff
UcbData8JisuanYuTuiduanSiweiZhongwenban/img/__init__.py
UcbData8JisuanYuTuiduanSiweiZhongwenban/img/annotator-glyph-sprite.png
UcbData8JisuanYuTuiduanSiweiZhongwenban/img/annotator-icon-sprite.png
UcbData8JisuanYuTuiduanSiweiZhongwenban/img/apple-touch-icon.png
UcbData8JisuanYuTuiduanSiweiZhongwenban/img/cancelfullscreen.png
UcbData8JisuanYuTuiduanSiweiZhongwenban/img/close.png
UcbData8JisuanYuTuiduanSiweiZhongwenban/img/fullscreen.png
UcbData8JisuanYuTuiduanSiweiZhongwenban/img/loader.gif
UcbData8JisuanYuTuiduanSiweiZhongwenban/img/menu-icon.png
UcbData8JisuanYuTuiduanSiweiZhongwenban/img/save.png
UcbData8JisuanYuTuiduanSiweiZhongwenban/img/saved.png
UcbData8JisuanYuTuiduanSiweiZhongwenban/img/settings-s.png
UcbData8JisuanYuTuiduanSiweiZhongwenban/img/settings.png
UcbData8JisuanYuTuiduanSiweiZhongwenban/img/star.png
UcbData8JisuanYuTuiduanSiweiZhongwenban/js/__init__.py
UcbData8JisuanYuTuiduanSiweiZhongwenban/js/epub.js
UcbData8JisuanYuTuiduanSiweiZhongwenban/js/epub.min.js
UcbData8JisuanYuTuiduanSiweiZhongwenban/js/epub.min.map
UcbData8JisuanYuTuiduanSiweiZhongwenban/js/hooks.min.js
UcbData8JisuanYuTuiduanSiweiZhongwenban/js/hooks.min.map
ucb_data8_jisuan_yu_tuiduan_siwei_zhongwenban-2024.3.4.0.dist-info/METADATA
ucb_data8_jisuan_yu_tuiduan_siwei_zhongwenban-2024.3.4.0.dist-info/WHEEL
ucb_data8_jisuan_yu_tuiduan_siwei_zhongwenban-2024.3.4.0.dist-info/entry_points.txt
ucb_data8_jisuan_yu_tuiduan_siwei_zhongwenban-2024.3.4.0.dist-info/top_level.txt
ucb_data8_jisuan_yu_tuiduan_siwei_zhongwenban-2024.3.4.0.dist-info/RECORD
